djm8/__init__.py
djm8/routes.py
djm8-0.1.1.dist-info/METADATA
djm8-0.1.1.dist-info/WHEEL
djm8-0.1.1.dist-info/RECORD
